{
    "$schema": "http://json-schema.org/draft-06/schema#",
    "$ref": "#/definitions/Country3Schema",
    "definitions": {
        "Country3Schema": {
            "type": "object",
            "additionalProperties": false,
            "properties": {
                "country_information": {
                    "$ref": "#/definitions/CountryInformation"
                }
            },
            "required": [
                "country_information"
            ],
            "title": "Country3Schema"
        },
        "CountryInformation": {
            "type": "object",
            "additionalProperties": false,
            "properties": {
                "country_name": {
                    "type": "string"
                },
                "continent_name": {
                    "type": "string"
                },
                "continent_code": {
                    "type": "string"
                },
                "subdivisions_1": {
                    "$ref": "#/definitions/Subdivisions1"
                }
            },
            "required": [
                "country_name",
                "continent_code",
                "continent_name",
                "subdivisions_1"
            ],
            "title": "CountryInformation"
        },
        "Subdivisions1": {
            "type": "object",
            "additionalProperties": false,
            "properties": {
                "sub_division_1_name": {
                    "type": "string"
                },
                "pincode": {
                    "type": "array",
                    "items": {"type": "integer"}
                }
            },
            "required": [
                "sub_division_1_name",
                "pincode"
            ],
            "title": "Subdivisions1"
        }
    }
}
